github_repo_lister/__init__.py
github_repo_lister-2025.9.131919.dist-info/licenses/LICENSE
github_repo_lister-2025.9.131919.dist-info/METADATA
github_repo_lister-2025.9.131919.dist-info/WHEEL
github_repo_lister-2025.9.131919.dist-info/top_level.txt
github_repo_lister-2025.9.131919.dist-info/RECORD
