Metadata-Version: 2.4
Name: github_repo_lister
Version: 2025.9.131919
Summary: a simple python function that takes ENV var GITHUB_TOKEN,  and name of a user gihub and return JSON of all repositories of that github user
Author-email: Eugene Evstafev <hi@eugene.plus>
License: MIT License
Project-URL: Repository, https://pypi.org/project/github_repo_lister/
Requires-Python: >=3.9
License-File: LICENSE
Dynamic: license-file
